MANIFEST.in
README.md
setup.py
akoteka/__init__.py
akoteka/accessories.py
akoteka/constants.py
akoteka/handle_property.py
akoteka/health_check.py
akoteka/language_fix.py
akoteka.egg-info/PKG-INFO
akoteka.egg-info/SOURCES.txt
akoteka.egg-info/dependency_links.txt
akoteka.egg-info/entry_points.txt
akoteka.egg-info/not-zip-safe
akoteka.egg-info/requires.txt
akoteka.egg-info/top_level.txt
akoteka/dict/resources.properties
akoteka/dict/resources_en.properties
akoteka/dict/resources_hu.properties
akoteka/gui/__init__.py
akoteka/gui/advanced_filter_holder.py
akoteka/gui/card_panel.py
akoteka/gui/configuration_dialog.py
akoteka/gui/control_buttons_holder.py
akoteka/gui/fast_filter_holder.py
akoteka/gui/main_window.py
akoteka/gui/pyqt_import.py
akoteka/gui/img/advanced-search-button-off.png
akoteka/gui/img/advanced-search-button-on.png
akoteka/gui/img/akoteka.png
akoteka/gui/img/back-button-off.png
akoteka/gui/img/back-button.png
akoteka/gui/img/best-off.png
akoteka/gui/img/best-on.png
akoteka/gui/img/cogwheel-button.png
akoteka/gui/img/empty.png
akoteka/gui/img/fast-search-button-off.png
akoteka/gui/img/fast-search-button-on.png
akoteka/gui/img/favorite-off.png
akoteka/gui/img/favorite-on.png
akoteka/gui/img/folder.png
akoteka/gui/img/new-off.png
akoteka/gui/img/new-on.png
akoteka/gui/img/play-button-off.png
akoteka/gui/img/play-button-on.png
akoteka/gui/img/stop-button-off.png
akoteka/gui/img/stop-button-on.png
akoteka/setup/__init__.py
akoteka/setup/setup.ini
akoteka/setup/setup.py
aqfilter/__init__.py
aqfilter/aqfilter.py
cardholder/__init__.py
cardholder/cardholder.py
cardholder/img/spinner.gif