Metadata-Version: 1.1
Name: akoteka
Version: 1.1.2
Summary: Videoteka
Home-page: http://github.com/dallaszkorben/akoteka
Author: dallaszkorben
Author-email: dallaszkorben@gmail.com
License: MIT
Platform: UNKNOWN
Classifier: Programming Language :: Python
Classifier: Programming Language :: Python :: 3
Classifier: Operating System :: OS Independent
